excel_base/__init__.py
excel_base/compat.py
excel_base/excel.py
excel_base-1.0.4.dist-info/METADATA
excel_base-1.0.4.dist-info/WHEEL
excel_base-1.0.4.dist-info/top_level.txt
excel_base-1.0.4.dist-info/RECORD
